parseridge/__init__.py
parseridge/corpus/__init__.py
parseridge/corpus/corpus.py
parseridge/corpus/relations.py
parseridge/corpus/sentence.py
parseridge/corpus/signature.py
parseridge/corpus/token.py
parseridge/corpus/training_data.py
parseridge/corpus/treebank.py
parseridge/corpus/vocabulary.py
parseridge/parser/__init__.py
parseridge/parser/activation.py
parseridge/parser/configuration.py
parseridge/parser/evaluation/__init__.py
parseridge/parser/evaluation/callbacks/__init__.py
parseridge/parser/evaluation/callbacks/attention_reporter_callback.py
parseridge/parser/evaluation/callbacks/base_eval_callback.py
parseridge/parser/evaluation/callbacks/csv_callback.py
parseridge/parser/evaluation/callbacks/google_sheets_callback.py
parseridge/parser/evaluation/callbacks/handler.py
parseridge/parser/evaluation/callbacks/progress_bar_callback.py
parseridge/parser/evaluation/callbacks/save_parsed_sentences_callback.py
parseridge/parser/evaluation/callbacks/simple_logger_callback.py
parseridge/parser/evaluation/callbacks/yaml_callback.py
parseridge/parser/evaluation/conll_eval.py
parseridge/parser/evaluation/evaluator.py
parseridge/parser/loss.py
parseridge/parser/model.py
parseridge/parser/modules/add_and_norm_layer.py
parseridge/parser/modules/attention/__init__.py
parseridge/parser/modules/attention/positional_embeddings.py
parseridge/parser/modules/attention/positional_encodings.py
parseridge/parser/modules/attention/self_attention_layer.py
parseridge/parser/modules/attention/similarity_functions.py
parseridge/parser/modules/attention/soft_attention.py
parseridge/parser/modules/attention/universal_attention.py
parseridge/parser/modules/configuration_encoder.py
parseridge/parser/modules/data_parallel.py
parseridge/parser/modules/external_embeddings.py
parseridge/parser/modules/gaussian_noise.py
parseridge/parser/modules/identity.py
parseridge/parser/modules/input_encoder.py
parseridge/parser/modules/mlp.py
parseridge/parser/modules/rnn.py
parseridge-0.1.0.dist-info/LICENSE
parseridge-0.1.0.dist-info/WHEEL
parseridge-0.1.0.dist-info/METADATA
parseridge-0.1.0.dist-info/RECORD
